turnstile_codevalidator-1.1.dist-info/WHEEL
turnstile_codevalidator-1.1.dist-info/DESCRIPTION.rst
turnstile_codevalidator-1.1.dist-info/entry_points.txt
turnstile_codevalidator-1.1.dist-info/metadata.json
turnstile_codevalidator-1.1.dist-info/RECORD
turnstile_codevalidator-1.1.dist-info/top_level.txt
turnstile_codevalidator-1.1.dist-info/METADATA
turnstile_codevalidator/__init__.py
turnstile_codevalidator/check.py
turnstile_codevalidator/command.py
